bionty_base/__init__.py
bionty_base/_display_sources.py
bionty_base/_ontology.py
bionty_base/_public_ontology.py
bionty_base/_settings.py
bionty_base/_sync_sources.py
bionty_base/sources.yaml
bionty_base/dev/__init__.py
bionty_base/dev/_handle_sources.py
bionty_base/dev/_io.py
bionty_base/dev/_md5.py
bionty_base/entities/__init__.py
bionty_base/entities/_bfxpipeline.py
bionty_base/entities/_biosample.py
bionty_base/entities/_cellline.py
bionty_base/entities/_cellmarker.py
bionty_base/entities/_celltype.py
bionty_base/entities/_developmentalstage.py
bionty_base/entities/_disease.py
bionty_base/entities/_drug.py
bionty_base/entities/_ethnicity.py
bionty_base/entities/_experimentalfactor.py
bionty_base/entities/_gene.py
bionty_base/entities/_organism.py
bionty_base/entities/_pathway.py
bionty_base/entities/_phenotype.py
bionty_base/entities/_protein.py
bionty_base/entities/_shared_docstrings.py
bionty_base/entities/_tissue.py
bionty_base-0.38.0.dist-info/LICENSE
bionty_base-0.38.0.dist-info/WHEEL
bionty_base-0.38.0.dist-info/METADATA
bionty_base-0.38.0.dist-info/RECORD
