Metadata-Version: 2.1
Name: bionty-base
Version: 0.38.0
Summary: Bionty.
Author-email: Lamin Labs <laminlabs@gmail.com>
Requires-Python: >=3.8
Classifier: License :: OSI Approved :: Apache Software License
Classifier: Programming Language :: Python :: 3.8
Classifier: Programming Language :: Python :: 3.9
Classifier: Programming Language :: Python :: 3.10
Classifier: Programming Language :: Python :: 3.11
Requires-Dist: pronto>=2.5.4, <2.5.6
Requires-Dist: lamin_utils>=0.12.0
Requires-Dist: pyyaml
Requires-Dist: pandas
Requires-Dist: pyarrow
Requires-Dist: botocore
Requires-Dist: rich
Requires-Dist: filelock
Requires-Dist: rapidfuzz
Requires-Dist: requests
Requires-Dist: pre-commit ; extra == "dev"
Requires-Dist: pytest>=6.0 ; extra == "dev"
Requires-Dist: pytest-cov ; extra == "dev"
Requires-Dist: laminci ; extra == "dev"
Requires-Dist: nbproject-test ; extra == "dev"
Requires-Dist: bioregistry ; extra == "dev"
Requires-Dist: sqlalchemy ; extra == "dev"
Requires-Dist: mysqlclient ; extra == "dev"
Requires-Dist: mysql-connector-python ; extra == "dev"
Project-URL: Home, https://github.com/laminlabs/bionty-base
Provides-Extra: dev
